xl_router/__init__.py
xl_router/restful.py
xl_router/router.py
xl_router/decorators/__init__.py
xl_router/exceptions/__init__.py
xl_router/utils/__init__.py
xl_router/utils/memory.py
xl_router/utils/session.py
xl_router/utils/base/json.py
xl_router-1.1.3.dist-info/METADATA
xl_router-1.1.3.dist-info/WHEEL
xl_router-1.1.3.dist-info/licenses/LICENSE
xl_router-1.1.3.dist-info/RECORD
