Metadata-Version: 2.4
Name: xl-router
Version: 1.1.3
Summary: xilong router library
Project-URL: Homepage, https://git.xilonglab.com/xilong/xl-router
Project-URL: Bug Tracker, https://git.xilonglab.com/xilong/xl-router/issues
Author-email: xilong <xilonglab@163.com>
License-File: LICENSE
Classifier: License :: OSI Approved :: MIT License
Classifier: Operating System :: OS Independent
Classifier: Programming Language :: Python :: 3
Requires-Python: >=3.7
Requires-Dist: flask==2.2.2
Requires-Dist: jsonschema==4.17.3
Requires-Dist: pyyaml==6.0.1
Requires-Dist: xl-memory==0.1.3
